termnotes/__init__.py
termnotes/calendar.py
termnotes/main.py
termnotes-30.4.dist-info/METADATA
termnotes-30.4.dist-info/WHEEL
termnotes-30.4.dist-info/entry_points.txt
termnotes-30.4.dist-info/top_level.txt
termnotes-30.4.dist-info/RECORD
