Metadata-Version: 2.4
Name: termnotes
Version: 30.4
Classifier: Programming Language :: Python :: 3
Classifier: Programming Language :: Python :: 3.7
Classifier: License :: OSI Approved :: MIT License
Classifier: Operating System :: OS Independent
Requires-Python: >=3.6
Requires-Dist: appdirs
Requires-Dist: gnureadline
Requires-Dist: pyperclip
Requires-Dist: rich
Requires-Dist: termcolor
Dynamic: classifier
Dynamic: requires-dist
Dynamic: requires-python
